examples/local_simple_taco.py
examples/testnet_compound_multichain_taco.py
examples/testnet_simple_taco.py
examples/pre/finnegans_wake_demo/finnegans-wake-demo-l2.py
examples/pre/heartbeat_demo/alicia.py
examples/pre/heartbeat_demo/doctor.py
examples/pre/heartbeat_demo/doctor_keys.py
examples/pre/heartbeat_demo/heart_monitor.py
newsfragments/validate_files.py
nucypher/__about__.py
nucypher/__init__.py
nucypher/exceptions.py
nucypher/types.py
nucypher/acumen/__init__.py
nucypher/acumen/nicknames.py
nucypher/acumen/perception.py
nucypher/acumen/web_colors.json
nucypher/acumen/zodiac.json
nucypher/blockchain/__init__.py
nucypher/blockchain/eth/__init__.py
nucypher/blockchain/eth/actors.py
nucypher/blockchain/eth/agents.py
nucypher/blockchain/eth/clients.py
nucypher/blockchain/eth/constants.py
nucypher/blockchain/eth/decorators.py
nucypher/blockchain/eth/domains.py
nucypher/blockchain/eth/events.py
nucypher/blockchain/eth/interfaces.py
nucypher/blockchain/eth/models.py
nucypher/blockchain/eth/providers.py
nucypher/blockchain/eth/registry.py
nucypher/blockchain/eth/token.py
nucypher/blockchain/eth/utils.py
nucypher/blockchain/eth/contract_registry/lynx.json
nucypher/blockchain/eth/contract_registry/mainnet.json
nucypher/blockchain/eth/contract_registry/tapir.json
nucypher/blockchain/eth/signers/__init__.py
nucypher/blockchain/eth/signers/base.py
nucypher/blockchain/eth/signers/software.py
nucypher/blockchain/eth/trackers/__init__.py
nucypher/blockchain/eth/trackers/bonding.py
nucypher/blockchain/eth/trackers/dkg.py
nucypher/blockchain/eth/trackers/prometheus.py
nucypher/blockchain/middleware/__init__.py
nucypher/blockchain/middleware/retry.py
nucypher/characters/__init__.py
nucypher/characters/banners.py
nucypher/characters/base.py
nucypher/characters/chaotic.py
nucypher/characters/lawful.py
nucypher/characters/unlawful.py
nucypher/cli/__init__.py
nucypher/cli/config.py
nucypher/cli/literature.py
nucypher/cli/main.py
nucypher/cli/options.py
nucypher/cli/types.py
nucypher-7.6.1.dist-info/licenses/LICENSE
nucypher-7.6.1.dist-info/METADATA
nucypher-7.6.1.dist-info/WHEEL
nucypher-7.6.1.dist-info/entry_points.txt
nucypher-7.6.1.dist-info/top_level.txt
nucypher-7.6.1.dist-info/zip-safe
nucypher-7.6.1.dist-info/RECORD
