Metadata-Version: 2.4
Name: nucypher
Version: 7.6.1
Summary: A threshold access control application to empower privacy in decentralized systems.
Home-page: https://github.com/nucypher/nucypher
Author: NuCypher
Author-email: dev@nucypher.com
License: GNU Affero General Public License, Version 3
Keywords: threshold access control,distributed key generation
Classifier: Development Status :: 3 - Alpha
Classifier: Intended Audience :: Developers
Classifier: Natural Language :: English
Classifier: Operating System :: OS Independent
Classifier: Programming Language :: Python
Classifier: Programming Language :: Python :: 3 :: Only
Classifier: Programming Language :: Python :: 3.10
Classifier: Programming Language :: Python :: 3.11
Classifier: Programming Language :: Python :: 3.12
Classifier: Topic :: Security
Requires-Python: >=3
License-File: LICENSE
Requires-Dist: abnf==2.4.0; python_version >= "3.10" and python_version < "4.0"
Requires-Dist: aiohappyeyeballs==2.6.1; python_version >= "3.10" and python_version < "4"
Requires-Dist: aiohttp==3.12.15; python_version >= "3.10" and python_version < "4"
Requires-Dist: aiosignal==1.4.0; python_version >= "3.10" and python_version < "4"
Requires-Dist: annotated-types==0.7.0; python_version >= "3.10" and python_version < "4"
Requires-Dist: appdirs==1.4.4; python_version >= "3.10" and python_version < "4"
Requires-Dist: async-timeout==5.0.1; python_version >= "3.10" and python_version < "3.11"
Requires-Dist: attrs==25.3.0; python_version >= "3.10" and python_version < "4"
Requires-Dist: atxm==0.5.0; python_version >= "3.10" and python_version < "4"
Requires-Dist: autobahn==24.4.2; python_version >= "3.10" and python_version < "4"
Requires-Dist: automat==25.4.16; python_version >= "3.10" and python_version < "4"
Requires-Dist: bitarray==3.7.1; python_version >= "3.10" and python_version < "4"
Requires-Dist: blinker==1.9.0; python_version >= "3.10" and python_version < "4"
Requires-Dist: bytestring-splitter==2.4.1; python_version >= "3.10" and python_version < "4"
Requires-Dist: certifi==2025.8.3; python_version >= "3.10" and python_version < "4"
Requires-Dist: cffi==2.0.0; python_version >= "3.10" and platform_python_implementation != "PyPy" and python_version < "4"
Requires-Dist: charset-normalizer==3.4.3; python_version >= "3.10" and python_version < "4"
Requires-Dist: ckzg==1.0.2; python_version >= "3.10" and python_version < "4"
Requires-Dist: click==8.3.0; python_version >= "3.10" and python_version < "4"
Requires-Dist: colorama==0.4.6; python_version >= "3.10" and python_version < "4"
Requires-Dist: constant-sorrow==0.1.0a9; python_version >= "3.10" and python_version < "4"
Requires-Dist: constantly==23.10.4; python_version >= "3.10" and python_version < "4"
Requires-Dist: cryptography==46.0.1; python_version >= "3.10" and python_version < "4"
Requires-Dist: cytoolz==1.0.1; python_version >= "3.10" and python_version < "4" and implementation_name == "cpython"
Requires-Dist: dateparser==1.2.2; python_version >= "3.10" and python_version < "4"
Requires-Dist: eth-abi==5.2.0; python_version >= "3.10" and python_version < "4"
Requires-Dist: eth-account==0.11.3; python_version >= "3.10" and python_version < "4"
Requires-Dist: eth-hash==0.7.1; python_version >= "3.10" and python_version < "4"
Requires-Dist: eth-hash[pycryptodome]==0.7.1; python_version >= "3.10" and python_version < "4"
Requires-Dist: eth-keyfile==0.9.1; python_version >= "3.10" and python_version < "4"
Requires-Dist: eth-keys==0.7.0; python_version >= "3.10" and python_version < "4"
Requires-Dist: eth-rlp==1.0.1; python_version >= "3.10" and python_version < "4"
Requires-Dist: eth-typing==3.5.2; python_version >= "3.10" and python_version < "4"
Requires-Dist: eth-utils==2.3.2; python_version >= "3.10" and python_version < "4"
Requires-Dist: flask==3.1.2; python_version >= "3.10" and python_version < "4"
Requires-Dist: frozenlist==1.7.0; python_version >= "3.10" and python_version < "4"
Requires-Dist: hendrix==5.0.0; python_version >= "3.10" and python_version < "4"
Requires-Dist: hexbytes==0.3.1; python_version >= "3.10" and python_version < "4"
Requires-Dist: humanize==4.13.0; python_version >= "3.10" and python_version < "4"
Requires-Dist: hyperlink==21.0.0; python_version >= "3.10" and python_version < "4"
Requires-Dist: idna==3.10; python_version >= "3.10" and python_version < "4"
Requires-Dist: incremental==24.7.2; python_version >= "3.10" and python_version < "4"
Requires-Dist: itsdangerous==2.2.0; python_version >= "3.10" and python_version < "4"
Requires-Dist: jinja2==3.1.6; python_version >= "3.10" and python_version < "4"
Requires-Dist: jsonpath-ng==1.7.0; python_version >= "3.10" and python_version < "4"
Requires-Dist: jsonschema-specifications==2025.9.1; python_version >= "3.10" and python_version < "4"
Requires-Dist: jsonschema==4.25.1; python_version >= "3.10" and python_version < "4"
Requires-Dist: lru-dict==1.2.0; python_version >= "3.10" and python_version < "4"
Requires-Dist: mako==1.3.10; python_version >= "3.10" and python_version < "4"
Requires-Dist: markupsafe==3.0.2; python_version >= "3.10" and python_version < "4"
Requires-Dist: marshmallow==3.26.1; python_version >= "3.10" and python_version < "4"
Requires-Dist: maya==0.6.1; python_version >= "3.10" and python_version < "4"
Requires-Dist: mnemonic==0.21; python_version >= "3.10" and python_version < "4"
Requires-Dist: msgpack-python==0.5.6; python_version >= "3.10" and python_version < "4"
Requires-Dist: multidict==6.6.4; python_version >= "3.10" and python_version < "4"
Requires-Dist: nucypher-core==0.15.0; python_version >= "3.10" and python_version < "4"
Requires-Dist: nucypher-pychalk==2.0.2; python_version >= "3.10" and python_version < "4"
Requires-Dist: nucypher-snaptime==0.2.5; python_version >= "3.10" and python_version < "4"
Requires-Dist: packaging==23.2; python_version >= "3.10" and python_version < "4"
Requires-Dist: parsimonious==0.10.0; python_version >= "3.10" and python_version < "4"
Requires-Dist: pendulum==3.1.0; python_version >= "3.10" and python_version < "4"
Requires-Dist: ply==3.11; python_version >= "3.10" and python_version < "4"
Requires-Dist: prometheus-client==0.23.1; python_version >= "3.10" and python_version < "4"
Requires-Dist: propcache==0.3.2; python_version >= "3.10" and python_version < "4"
Requires-Dist: protobuf==6.32.1; python_version >= "3.10" and python_version < "4"
Requires-Dist: py-ecc==8.0.0; python_version >= "3.10" and python_version < "4"
Requires-Dist: pyasn1-modules==0.4.2; python_version >= "3.10" and python_version < "4"
Requires-Dist: pyasn1==0.6.1; python_version >= "3.10" and python_version < "4"
Requires-Dist: pycparser==2.23; python_version >= "3.10" and platform_python_implementation != "PyPy" and python_version < "4" and implementation_name != "PyPy"
Requires-Dist: pycryptodome==3.23.0; python_version >= "3.10" and python_version < "4"
Requires-Dist: pydantic-core==2.33.2; python_version >= "3.10" and python_version < "4.0"
Requires-Dist: pydantic==2.11.9; python_version >= "3.10" and python_version < "4"
Requires-Dist: pyjwt[crypto]==2.10.1; python_version >= "3.10" and python_version < "4"
Requires-Dist: pynacl==1.6.0; python_version >= "3.10" and python_version < "4"
Requires-Dist: pyopenssl==25.3.0; python_version >= "3.10" and python_version < "4"
Requires-Dist: python-dateutil==2.9.0.post0; python_version >= "3.10" and python_version < "4"
Requires-Dist: python-statemachine==2.3.4; python_version >= "3.10" and python_version < "4"
Requires-Dist: pytz==2025.2; python_version >= "3.10" and python_version < "4"
Requires-Dist: pyunormalize==16.0.0; python_version >= "3.10" and python_version < "4"
Requires-Dist: pywin32==311; python_version >= "3.10" and python_version < "4" and platform_system == "Windows"
Requires-Dist: referencing==0.36.2; python_version >= "3.10" and python_version < "4"
Requires-Dist: regex==2025.9.18; python_version >= "3.10" and python_version < "4"
Requires-Dist: requests==2.32.5; python_version >= "3.10" and python_version < "4"
Requires-Dist: rlp==4.1.0; python_version >= "3.10" and python_version < "4"
Requires-Dist: rpds-py==0.27.1; python_version >= "3.10" and python_version < "4"
Requires-Dist: service-identity==24.2.0; python_version >= "3.10" and python_version < "4"
Requires-Dist: setuptools==80.9.0; python_version >= "3.10" and python_version < "4"
Requires-Dist: siwe==4.2.0; python_version >= "3.10" and python_version < "4.0"
Requires-Dist: six==1.17.0; python_version >= "3.10" and python_version < "4"
Requires-Dist: tabulate==0.9.0; python_version >= "3.10" and python_version < "4"
Requires-Dist: time-machine==2.19.0; python_version >= "3.10" and python_version < "4"
Requires-Dist: tomli==2.2.1; python_version >= "3.10" and python_version < "3.11"
Requires-Dist: toolz==1.0.0; python_version >= "3.10" and python_version < "4" and (implementation_name == "pypy" or implementation_name == "cpython")
Requires-Dist: twisted==24.11.0; python_version >= "3.10" and python_version < "4"
Requires-Dist: txaio==25.6.1; python_version >= "3.10" and python_version < "4"
Requires-Dist: typing-extensions==4.15.0; python_version >= "3.10" and python_version < "4"
Requires-Dist: typing-inspection==0.4.1; python_version >= "3.10" and python_version < "4"
Requires-Dist: tzdata==2025.2; python_version >= "3.10" and python_version < "4"
Requires-Dist: tzlocal==5.3.1; python_version >= "3.10" and python_version < "4"
Requires-Dist: urllib3==2.5.0; python_version >= "3.10" and python_version < "4"
Requires-Dist: watchdog==3.0.0; python_version >= "3.10" and python_version < "4"
Requires-Dist: web3==6.20.1; python_version >= "3.10" and python_version < "4"
Requires-Dist: websockets==15.0.1; python_version >= "3.10" and python_version < "4"
Requires-Dist: werkzeug==3.1.3; python_version >= "3.10" and python_version < "4"
Requires-Dist: yarl==1.20.1; python_version >= "3.10" and python_version < "4"
Requires-Dist: zope-interface==8.0; python_version >= "3.10" and python_version < "4"
Provides-Extra: dev
Requires-Dist: abnf==2.4.0; (python_version >= "3.10" and python_version < "4.0") and extra == "dev"
Requires-Dist: aiohappyeyeballs==2.6.1; (python_version >= "3.10" and python_version < "4") and extra == "dev"
Requires-Dist: aiohttp==3.12.15; (python_version >= "3.10" and python_version < "4") and extra == "dev"
Requires-Dist: aiosignal==1.4.0; (python_version >= "3.10" and python_version < "4") and extra == "dev"
Requires-Dist: annotated-types==0.7.0; (python_version >= "3.10" and python_version < "4") and extra == "dev"
Requires-Dist: ape-solidity==0.8.5; (python_version >= "3.10" and python_version < "4") and extra == "dev"
Requires-Dist: appdirs==1.4.4; (python_version >= "3.10" and python_version < "4") and extra == "dev"
Requires-Dist: asttokens==3.0.0; (python_version >= "3.10" and python_version < "4") and extra == "dev"
Requires-Dist: async-timeout==5.0.1; (python_version >= "3.10" and python_version < "3.11") and extra == "dev"
Requires-Dist: attrs==25.3.0; (python_version >= "3.10" and python_version < "4") and extra == "dev"
Requires-Dist: atxm==0.5.0; (python_version >= "3.10" and python_version < "4") and extra == "dev"
Requires-Dist: autobahn==24.4.2; (python_version >= "3.10" and python_version < "4") and extra == "dev"
Requires-Dist: automat==25.4.16; (python_version >= "3.10" and python_version < "4") and extra == "dev"
Requires-Dist: base58==1.0.3; (python_version >= "3.10" and python_version < "4") and extra == "dev"
Requires-Dist: bitarray==3.7.1; (python_version >= "3.10" and python_version < "4") and extra == "dev"
Requires-Dist: blinker==1.9.0; (python_version >= "3.10" and python_version < "4") and extra == "dev"
Requires-Dist: bytestring-splitter==2.4.1; (python_version >= "3.10" and python_version < "4") and extra == "dev"
Requires-Dist: cached-property==2.0.1; (python_version >= "3.10" and python_version < "4") and extra == "dev"
Requires-Dist: certifi==2025.8.3; (python_version >= "3.10" and python_version < "4") and extra == "dev"
Requires-Dist: cffi==2.0.0; (python_version >= "3.10" and platform_python_implementation != "PyPy" and python_version < "4") and extra == "dev"
Requires-Dist: cfgv==3.4.0; (python_version >= "3.10" and python_version < "4") and extra == "dev"
Requires-Dist: charset-normalizer==3.4.3; (python_version >= "3.10" and python_version < "4") and extra == "dev"
Requires-Dist: ckzg==1.0.2; (python_version >= "3.10" and python_version < "4") and extra == "dev"
Requires-Dist: click==8.3.0; (python_version >= "3.10" and python_version < "4") and extra == "dev"
Requires-Dist: colorama==0.4.6; (python_version >= "3.10" and python_version < "4") and extra == "dev"
Requires-Dist: constant-sorrow==0.1.0a9; (python_version >= "3.10" and python_version < "4") and extra == "dev"
Requires-Dist: constantly==23.10.4; (python_version >= "3.10" and python_version < "4") and extra == "dev"
Requires-Dist: coverage==7.10.7; (python_version >= "3.10" and python_version < "4") and extra == "dev"
Requires-Dist: coverage[toml]==7.10.7; (python_version >= "3.10" and python_version < "4") and extra == "dev"
Requires-Dist: cryptography==46.0.1; (python_version >= "3.10" and python_version < "4") and extra == "dev"
Requires-Dist: cytoolz==1.0.1; (python_version >= "3.10" and python_version < "4" and implementation_name == "cpython") and extra == "dev"
Requires-Dist: dataclassy==0.11.1; (python_version >= "3.10" and python_version < "4") and extra == "dev"
Requires-Dist: dateparser==1.2.2; (python_version >= "3.10" and python_version < "4") and extra == "dev"
Requires-Dist: decorator==5.2.1; (python_version >= "3.10" and python_version < "4") and extra == "dev"
Requires-Dist: distlib==0.4.0; (python_version >= "3.10" and python_version < "4") and extra == "dev"
Requires-Dist: eip712==0.2.13; (python_version >= "3.10" and python_version < "4") and extra == "dev"
Requires-Dist: eth-abi==5.2.0; (python_version >= "3.10" and python_version < "4") and extra == "dev"
Requires-Dist: eth-account==0.11.3; (python_version >= "3.10" and python_version < "4") and extra == "dev"
Requires-Dist: eth-ape==0.8.12; (python_version >= "3.10" and python_version < "4") and extra == "dev"
Requires-Dist: eth-bloom==3.1.0; (python_version >= "3.10" and python_version < "4") and extra == "dev"
Requires-Dist: eth-hash==0.7.1; (python_version >= "3.10" and python_version < "4") and extra == "dev"
Requires-Dist: eth-hash[pycryptodome]==0.7.1; (python_version >= "3.10" and python_version < "4") and extra == "dev"
Requires-Dist: eth-hash[pysha3]==0.7.1; (python_version >= "3.10" and python_version < "4" and implementation_name == "cpython") and extra == "dev"
Requires-Dist: eth-keyfile==0.9.1; (python_version >= "3.10" and python_version < "4") and extra == "dev"
Requires-Dist: eth-keys==0.7.0; (python_version >= "3.10" and python_version < "4") and extra == "dev"
Requires-Dist: eth-pydantic-types==0.1.3; (python_version >= "3.10" and python_version < "4") and extra == "dev"
Requires-Dist: eth-rlp==1.0.1; (python_version >= "3.10" and python_version < "4") and extra == "dev"
Requires-Dist: eth-tester[py-evm]==0.11.0b2; (python_version >= "3.10" and python_version < "4") and extra == "dev"
Requires-Dist: eth-typing==3.5.2; (python_version >= "3.10" and python_version < "4") and extra == "dev"
Requires-Dist: eth-utils==2.3.2; (python_version >= "3.10" and python_version < "4") and extra == "dev"
Requires-Dist: ethpm-types==0.6.25; (python_version >= "3.10" and python_version < "4") and extra == "dev"
Requires-Dist: evm-trace==0.2.4; (python_version >= "3.10" and python_version < "4") and extra == "dev"
Requires-Dist: evmchains==0.0.13; (python_version >= "3.10" and python_version < "4") and extra == "dev"
Requires-Dist: exceptiongroup==1.3.0; (python_version >= "3.10" and python_version < "3.11") and extra == "dev"
Requires-Dist: executing==2.2.1; (python_version >= "3.10" and python_version < "4") and extra == "dev"
Requires-Dist: filelock==3.19.1; (python_version >= "3.10" and python_version < "4") and extra == "dev"
Requires-Dist: flask==3.1.2; (python_version >= "3.10" and python_version < "4") and extra == "dev"
Requires-Dist: frozenlist==1.7.0; (python_version >= "3.10" and python_version < "4") and extra == "dev"
Requires-Dist: greenlet==3.2.4; (python_version >= "3.10" and python_version < "4") and extra == "dev"
Requires-Dist: hendrix==5.0.0; (python_version >= "3.10" and python_version < "4") and extra == "dev"
Requires-Dist: hexbytes==0.3.1; (python_version >= "3.10" and python_version < "4") and extra == "dev"
Requires-Dist: humanize==4.13.0; (python_version >= "3.10" and python_version < "4") and extra == "dev"
Requires-Dist: hyperlink==21.0.0; (python_version >= "3.10" and python_version < "4") and extra == "dev"
Requires-Dist: identify==2.6.14; (python_version >= "3.10" and python_version < "4") and extra == "dev"
Requires-Dist: idna==3.10; (python_version >= "3.10" and python_version < "4") and extra == "dev"
Requires-Dist: ijson==3.4.0; (python_version >= "3.10" and python_version < "4") and extra == "dev"
Requires-Dist: incremental==24.7.2; (python_version >= "3.10" and python_version < "4") and extra == "dev"
Requires-Dist: iniconfig==2.1.0; (python_version >= "3.10" and python_version < "4") and extra == "dev"
Requires-Dist: ipython==8.37.0; (python_version >= "3.10" and python_version < "4") and extra == "dev"
Requires-Dist: itsdangerous==2.2.0; (python_version >= "3.10" and python_version < "4") and extra == "dev"
Requires-Dist: jedi==0.19.2; (python_version >= "3.10" and python_version < "4") and extra == "dev"
Requires-Dist: jinja2==3.1.6; (python_version >= "3.10" and python_version < "4") and extra == "dev"
Requires-Dist: jsonpath-ng==1.7.0; (python_version >= "3.10" and python_version < "4") and extra == "dev"
Requires-Dist: jsonschema-specifications==2025.9.1; (python_version >= "3.10" and python_version < "4") and extra == "dev"
Requires-Dist: jsonschema==4.25.1; (python_version >= "3.10" and python_version < "4") and extra == "dev"
Requires-Dist: lazyasd==0.1.4; (python_version >= "3.10" and python_version < "4") and extra == "dev"
Requires-Dist: lru-dict==1.2.0; (python_version >= "3.10" and python_version < "4") and extra == "dev"
Requires-Dist: mako==1.3.10; (python_version >= "3.10" and python_version < "4") and extra == "dev"
Requires-Dist: markdown-it-py==4.0.0; (python_version >= "3.10" and python_version < "4") and extra == "dev"
Requires-Dist: markupsafe==3.0.2; (python_version >= "3.10" and python_version < "4") and extra == "dev"
Requires-Dist: marshmallow==3.26.1; (python_version >= "3.10" and python_version < "4") and extra == "dev"
Requires-Dist: matplotlib-inline==0.1.7; (python_version >= "3.10" and python_version < "4") and extra == "dev"
Requires-Dist: maya==0.6.1; (python_version >= "3.10" and python_version < "4") and extra == "dev"
Requires-Dist: mdurl==0.1.2; (python_version >= "3.10" and python_version < "4") and extra == "dev"
Requires-Dist: mnemonic==0.21; (python_version >= "3.10" and python_version < "4") and extra == "dev"
Requires-Dist: morphys==1.0; (python_version >= "3.10" and python_version < "4") and extra == "dev"
Requires-Dist: msgpack-python==0.5.6; (python_version >= "3.10" and python_version < "4") and extra == "dev"
Requires-Dist: msgspec==0.19.0; (python_version >= "3.10" and python_version < "3.13") and extra == "dev"
Requires-Dist: multidict==6.6.4; (python_version >= "3.10" and python_version < "4") and extra == "dev"
Requires-Dist: nodeenv==1.9.1; (python_version >= "3.10" and python_version < "4") and extra == "dev"
Requires-Dist: nucypher-core==0.15.0; (python_version >= "3.10" and python_version < "4") and extra == "dev"
Requires-Dist: nucypher-pychalk==2.0.2; (python_version >= "3.10" and python_version < "4") and extra == "dev"
Requires-Dist: nucypher-snaptime==0.2.5; (python_version >= "3.10" and python_version < "4") and extra == "dev"
Requires-Dist: numpy==1.26.4; (python_version >= "3.10" and python_version < "4") and extra == "dev"
Requires-Dist: packaging==23.2; (python_version >= "3.10" and python_version < "4") and extra == "dev"
Requires-Dist: pandas==2.3.2; (python_version >= "3.10" and python_version < "4") and extra == "dev"
Requires-Dist: parsimonious==0.10.0; (python_version >= "3.10" and python_version < "4") and extra == "dev"
Requires-Dist: parso==0.8.5; (python_version >= "3.10" and python_version < "4") and extra == "dev"
Requires-Dist: pendulum==3.1.0; (python_version >= "3.10" and python_version < "4") and extra == "dev"
Requires-Dist: pexpect==4.9.0; (python_version >= "3.10" and python_version < "4" and (sys_platform != "win32" and sys_platform != "emscripten")) and extra == "dev"
Requires-Dist: platformdirs==4.4.0; (python_version >= "3.10" and python_version < "4") and extra == "dev"
Requires-Dist: pluggy==1.6.0; (python_version >= "3.10" and python_version < "4") and extra == "dev"
Requires-Dist: ply==3.11; (python_version >= "3.10" and python_version < "4") and extra == "dev"
Requires-Dist: pre-commit==2.21.0; (python_version >= "3.10" and python_version < "4") and extra == "dev"
Requires-Dist: prometheus-client==0.23.1; (python_version >= "3.10" and python_version < "4") and extra == "dev"
Requires-Dist: prompt-toolkit==3.0.52; (python_version >= "3.10" and python_version < "4") and extra == "dev"
Requires-Dist: propcache==0.3.2; (python_version >= "3.10" and python_version < "4") and extra == "dev"
Requires-Dist: protobuf==6.32.1; (python_version >= "3.10" and python_version < "4") and extra == "dev"
Requires-Dist: ptyprocess==0.7.0; (python_version >= "3.10" and python_version < "4" and (sys_platform != "win32" and sys_platform != "emscripten")) and extra == "dev"
Requires-Dist: pure-eval==0.2.3; (python_version >= "3.10" and python_version < "4") and extra == "dev"
Requires-Dist: py-cid==0.3.1; (python_version >= "3.10" and python_version < "4") and extra == "dev"
Requires-Dist: py-ecc==8.0.0; (python_version >= "3.10" and python_version < "4") and extra == "dev"
Requires-Dist: py-evm==0.10.1b1; (python_version >= "3.10" and python_version < "4") and extra == "dev"
Requires-Dist: py-geth==5.6.0; (python_version >= "3.10" and python_version < "4") and extra == "dev"
Requires-Dist: py-multibase==1.0.3; (python_version >= "3.10" and python_version < "4") and extra == "dev"
Requires-Dist: py-multicodec==0.2.1; (python_version >= "3.10" and python_version < "4") and extra == "dev"
Requires-Dist: py-solc-x==2.0.4; (python_version >= "3.10" and python_version < "4") and extra == "dev"
Requires-Dist: pyasn1-modules==0.4.2; (python_version >= "3.10" and python_version < "4") and extra == "dev"
Requires-Dist: pyasn1==0.6.1; (python_version >= "3.10" and python_version < "4") and extra == "dev"
Requires-Dist: pycparser==2.23; (python_version >= "3.10" and platform_python_implementation != "PyPy" and python_version < "4" and implementation_name != "PyPy") and extra == "dev"
Requires-Dist: pycryptodome==3.23.0; (python_version >= "3.10" and python_version < "4") and extra == "dev"
Requires-Dist: pydantic-core==2.33.2; (python_version >= "3.10" and python_version < "4.0") and extra == "dev"
Requires-Dist: pydantic-settings==2.10.1; (python_version >= "3.10" and python_version < "4") and extra == "dev"
Requires-Dist: pydantic==2.11.9; (python_version >= "3.10" and python_version < "4") and extra == "dev"
Requires-Dist: pygments==2.19.2; (python_version >= "3.10" and python_version < "4") and extra == "dev"
Requires-Dist: pyjwt[crypto]==2.10.1; (python_version >= "3.10" and python_version < "4") and extra == "dev"
Requires-Dist: pymultihash==0.8.2; (python_version >= "3.10" and python_version < "4") and extra == "dev"
Requires-Dist: pynacl==1.6.0; (python_version >= "3.10" and python_version < "4") and extra == "dev"
Requires-Dist: pyopenssl==25.3.0; (python_version >= "3.10" and python_version < "4") and extra == "dev"
Requires-Dist: pytest-cov==7.0.0; (python_version >= "3.10" and python_version < "4") and extra == "dev"
Requires-Dist: pytest-mock==3.15.1; (python_version >= "3.10" and python_version < "4") and extra == "dev"
Requires-Dist: pytest-timeout==2.4.0; (python_version >= "3.10" and python_version < "4") and extra == "dev"
Requires-Dist: pytest-twisted==1.14.3; (python_version >= "3.10" and python_version < "4") and extra == "dev"
Requires-Dist: pytest==8.4.2; (python_version >= "3.10" and python_version < "4") and extra == "dev"
Requires-Dist: python-baseconv==1.2.2; (python_version >= "3.10" and python_version < "4") and extra == "dev"
Requires-Dist: python-dateutil==2.9.0.post0; (python_version >= "3.10" and python_version < "4") and extra == "dev"
Requires-Dist: python-dotenv==1.1.1; (python_version >= "3.10" and python_version < "4") and extra == "dev"
Requires-Dist: python-statemachine==2.3.4; (python_version >= "3.10" and python_version < "4") and extra == "dev"
Requires-Dist: pytz==2025.2; (python_version >= "3.10" and python_version < "4") and extra == "dev"
Requires-Dist: pyunormalize==16.0.0; (python_version >= "3.10" and python_version < "4") and extra == "dev"
Requires-Dist: pywin32==311; (python_version >= "3.10" and python_version < "4" and platform_system == "Windows") and extra == "dev"
Requires-Dist: pyyaml==6.0.2; (python_version >= "3.10" and python_version < "4") and extra == "dev"
Requires-Dist: referencing==0.36.2; (python_version >= "3.10" and python_version < "4") and extra == "dev"
Requires-Dist: regex==2025.9.18; (python_version >= "3.10" and python_version < "4") and extra == "dev"
Requires-Dist: requests==2.32.5; (python_version >= "3.10" and python_version < "4") and extra == "dev"
Requires-Dist: rich==13.9.4; (python_version >= "3.10" and python_version < "4") and extra == "dev"
Requires-Dist: rlp==4.1.0; (python_version >= "3.10" and python_version < "4") and extra == "dev"
Requires-Dist: rpds-py==0.27.1; (python_version >= "3.10" and python_version < "4") and extra == "dev"
Requires-Dist: safe-pysha3==1.0.5; (python_version >= "3.10" and python_version < "4" and implementation_name == "cpython") and extra == "dev"
Requires-Dist: semantic-version==2.10.0; (python_version >= "3.10" and python_version < "4") and extra == "dev"
Requires-Dist: service-identity==24.2.0; (python_version >= "3.10" and python_version < "4") and extra == "dev"
Requires-Dist: setuptools==80.9.0; (python_version >= "3.10" and python_version < "4") and extra == "dev"
Requires-Dist: siwe==4.2.0; (python_version >= "3.10" and python_version < "4.0") and extra == "dev"
Requires-Dist: six==1.17.0; (python_version >= "3.10" and python_version < "4") and extra == "dev"
Requires-Dist: sortedcontainers==2.4.0; (python_version >= "3.10" and python_version < "4") and extra == "dev"
Requires-Dist: sqlalchemy==2.0.43; (python_version >= "3.10" and python_version < "4") and extra == "dev"
Requires-Dist: stack-data==0.6.3; (python_version >= "3.10" and python_version < "4") and extra == "dev"
Requires-Dist: tabulate==0.9.0; (python_version >= "3.10" and python_version < "4") and extra == "dev"
Requires-Dist: time-machine==2.19.0; (python_version >= "3.10" and python_version < "4") and extra == "dev"
Requires-Dist: toml==0.10.2; (python_version >= "3.10" and python_version < "3.11") and extra == "dev"
Requires-Dist: tomli==2.2.1; (python_version >= "3.10" and python_full_version <= "3.11.0a6") and extra == "dev"
Requires-Dist: toolz==1.0.0; (python_version >= "3.10" and python_version < "4" and (implementation_name == "pypy" or implementation_name == "cpython")) and extra == "dev"
Requires-Dist: tqdm==4.67.1; (python_version >= "3.10" and python_version < "4") and extra == "dev"
Requires-Dist: traitlets==5.14.3; (python_version >= "3.10" and python_version < "4") and extra == "dev"
Requires-Dist: trie==3.1.0; (python_version >= "3.10" and python_version < "4") and extra == "dev"
Requires-Dist: twisted==24.11.0; (python_version >= "3.10" and python_version < "4") and extra == "dev"
Requires-Dist: txaio==25.6.1; (python_version >= "3.10" and python_version < "4") and extra == "dev"
Requires-Dist: types-requests==2.32.4.20250913; (python_version >= "3.10" and python_version < "4") and extra == "dev"
Requires-Dist: typing-extensions==4.15.0; (python_version >= "3.10" and python_version < "4") and extra == "dev"
Requires-Dist: typing-inspection==0.4.1; (python_version >= "3.10" and python_version < "4") and extra == "dev"
Requires-Dist: tzdata==2025.2; (python_version >= "3.10" and python_version < "4") and extra == "dev"
Requires-Dist: tzlocal==5.3.1; (python_version >= "3.10" and python_version < "4") and extra == "dev"
Requires-Dist: urllib3==2.5.0; (python_version >= "3.10" and python_version < "4") and extra == "dev"
Requires-Dist: varint==1.0.2; (python_version >= "3.10" and python_version < "4") and extra == "dev"
Requires-Dist: virtualenv==20.34.0; (python_version >= "3.10" and python_version < "4") and extra == "dev"
Requires-Dist: watchdog==3.0.0; (python_version >= "3.10" and python_version < "4") and extra == "dev"
Requires-Dist: wcwidth==0.2.14; (python_version >= "3.10" and python_version < "4") and extra == "dev"
Requires-Dist: web3==6.20.1; (python_version >= "3.10" and python_version < "4") and extra == "dev"
Requires-Dist: web3[tester]==6.20.1; (python_version >= "3.10" and python_version < "4") and extra == "dev"
Requires-Dist: websockets==15.0.1; (python_version >= "3.10" and python_version < "4") and extra == "dev"
Requires-Dist: werkzeug==3.1.3; (python_version >= "3.10" and python_version < "4") and extra == "dev"
Requires-Dist: yarl==1.20.1; (python_version >= "3.10" and python_version < "4") and extra == "dev"
Requires-Dist: zope-interface==8.0; (python_version >= "3.10" and python_version < "4") and extra == "dev"
Dynamic: author
Dynamic: author-email
Dynamic: classifier
Dynamic: description
Dynamic: description-content-type
Dynamic: home-page
Dynamic: keywords
Dynamic: license
Dynamic: license-file
Dynamic: provides-extra
Dynamic: requires-dist
Dynamic: requires-python
Dynamic: summary
